LICENSE
MANIFEST.in
README.md
setup.cfg
setup.py
bin/audio_convertio
src/audio_convertio/__init__.py
src/audio_convertio/audio_convertio.py
src/audio_convertio.egg-info/PKG-INFO
src/audio_convertio.egg-info/SOURCES.txt
src/audio_convertio.egg-info/dependency_links.txt
src/audio_convertio.egg-info/entry_points.txt
src/audio_convertio.egg-info/requires.txt
src/audio_convertio.egg-info/top_level.txt
src/audio_convertio/classes/__init__.py
src/audio_convertio/classes/audio_converter.py
src/audio_convertio/classes/custom_exceptions.py
src/audio_convertio/index/__init__.py
src/audio_convertio/index/index.py
src/audio_convertio/shared_library/__init__.py
src/audio_convertio/shared_library/arguments_validator.py