Metadata-Version: 2.1
Name: audio-convertio
Version: 0.2.0
Summary: Audio ConvertIO: Convert your audio files easily
Home-page: https://github.com/AudioConvertio/file-converter
Author: Bruno Dantas de Paiva
Author-email: bruno.dantas@poli.ufrj.br
License: MIT
Download-URL: https://github.com/AudioConvertio/file-converter/archive/refs/tags/v0.2.0.tar.gz
Project-URL: Bug Tracker, https://github.com/AudioConvertio/file-converter/issues/new?assignees=&labels=&template=bug_report.md&title=
Project-URL: Source, https://github.com/AudioConvertio/file-converter
Project-URL: Feature Request, https://github.com/AudioConvertio/file-converter/issues/new?assignees=&labels=&template=feature_request.md&title=
Platform: any
Classifier: Programming Language :: Python :: 3
Classifier: License :: OSI Approved :: MIT License
Classifier: Operating System :: OS Independent
Requires-Python: >=3.8
